README.md
setup.cfg
setup.py
RAPILite.egg-info/PKG-INFO
RAPILite.egg-info/SOURCES.txt
RAPILite.egg-info/dependency_links.txt
RAPILite.egg-info/requires.txt
RAPILite.egg-info/top_level.txt
reddit/Reddit.py
reddit/__init__.py
reddit/exceptions.py
reddit/types.py
reddit/utils.py