Metadata-Version: 2.1
Name: RAPILite
Version: 0.1.8
Summary: An asynchronous wrapper for Reddit's readonly API
Home-page: https://github.com/sudosnok/RAPILite
Author: sudosnok
License: MIT
Platform: UNKNOWN
Classifier: Development Status :: 3 - Alpha
Classifier: Intended Audience :: Developers
Classifier: License :: OSI Approved :: MIT License
Classifier: Programming Language :: Python :: 3.6
Requires-Python: >=3.6
